yta_numpy_resizer/__init__.py
yta_numpy_resizer-0.0.4.dist-info/licenses/LICENSE
yta_numpy_resizer-0.0.4.dist-info/METADATA
yta_numpy_resizer-0.0.4.dist-info/WHEEL
yta_numpy_resizer-0.0.4.dist-info/RECORD
