Metadata-Version: 2.4
Name: yta-numpy-resizer
Version: 0.0.4
Summary: Youtube Autonomous Numpy Resizer Module
License-File: LICENSE
Author: danialcala94
Author-email: danielalcalavalera@gmail.com
Requires-Python: ==3.9
Classifier: Programming Language :: Python :: 3
Classifier: Programming Language :: Python :: 3.9
Requires-Dist: numpy (>=0.0.1,<99.0.0)
Requires-Dist: opencv-python (>=0.0.1,<99.0.0)
